sgndrift/__init__.py
sgndrift/_version.py
sgndrift/bin/__init__.py
sgndrift/bin/estimate_drift.py
sgndrift/bin/plot_drift.py
sgndrift/bin/plot_drift_comparison.py
sgndrift/bin/plot_drift_super.py
sgndrift/bin/plot_drift_super_comp.py
sgndrift/bin/plot_drift_time.py
sgndrift/psd/__init__.py
sgndrift/psd/drift.py
sgndrift/psd/estimators.py
sgndrift/sinks/__init__.py
sgndrift/sinks/drift_sink.py
sgndrift/transforms/__init__.py
sgndrift/transforms/drift.py
sgndrift/transforms/psd.py
sgn_drift-0.1.0.dist-info/METADATA
sgn_drift-0.1.0.dist-info/WHEEL
sgn_drift-0.1.0.dist-info/entry_points.txt
sgn_drift-0.1.0.dist-info/top_level.txt
sgn_drift-0.1.0.dist-info/RECORD
