Metadata-Version: 2.4
Name: sgn-drift
Version: 0.1.0
Summary: PSD Drift Data Quality Extensions for the SGN Framework
Author-email: James Kennington <jmk7376@psu.edu>, Zach Yarbrough <jmk7376@psu.edu>, Joshua Black <jmk7376@psu.edu>
License-Expression: MPL-2.0
Project-URL: Homepage, https://git.ligo.org/james.kennington/sgn-drift
Project-URL: Documentation, https://docs.ligo.org/james.kennington/sgn-drift
Project-URL: Issues, https://git.ligo.org/james.kennington/sgn-drift/issues
Classifier: Programming Language :: Python :: 3
Classifier: Operating System :: OS Independent
Requires-Python: >=3.10
Requires-Dist: gwpy
Requires-Dist: h5py
Requires-Dist: igwn-ligolw
Requires-Dist: igwn-segments
Requires-Dist: lalsuite>=7.26
Requires-Dist: scipy<1.17
Requires-Dist: sgn>=0.4
Requires-Dist: sgn-ts>=0.4
Requires-Dist: sgn-ligo
Provides-Extra: test
Requires-Dist: pytest; extra == "test"
Requires-Dist: pytest-cov; extra == "test"
Requires-Dist: pytest-freezer; extra == "test"
Requires-Dist: pytest-markdown-docs; extra == "test"
Provides-Extra: docs
Requires-Dist: mkdocs; extra == "docs"
Requires-Dist: mkdocstrings; extra == "docs"
Requires-Dist: mkdocstrings-python; extra == "docs"
Requires-Dist: mkdocs-material; extra == "docs"
Requires-Dist: pymdown-extensions; extra == "docs"
Provides-Extra: lint
Requires-Dist: black; extra == "lint"
Requires-Dist: flake8; extra == "lint"
Requires-Dist: flake8-bandit; extra == "lint"
Requires-Dist: flake8-black; extra == "lint"
Requires-Dist: flake8-bugbear; extra == "lint"
Requires-Dist: flake8-future-annotations; extra == "lint"
Requires-Dist: flake8-isort; extra == "lint"
Requires-Dist: flake8-logging-format; extra == "lint"
Requires-Dist: flake8-pyproject; extra == "lint"
Requires-Dist: isort; extra == "lint"
Requires-Dist: mypy; extra == "lint"
Requires-Dist: mypy-extensions; extra == "lint"
Provides-Extra: dev
Requires-Dist: sgn-drift[docs]; extra == "dev"
Requires-Dist: sgn-drift[lint]; extra == "dev"
Requires-Dist: sgn-drift[test]; extra == "dev"
